chloryne/__init__.py
chloryne/_chloryne.cpython-37m-darwin.so
chloryne/ciphers.py
chloryne/keys.py
chloryne/mac.py
chloryne/misc.py
chloryne/password.py
chloryne/signers.py
chloryne-1.0.0.dist-info/LICENSE
chloryne-1.0.0.dist-info/METADATA
chloryne-1.0.0.dist-info/WHEEL
chloryne-1.0.0.dist-info/top_level.txt
chloryne-1.0.0.dist-info/RECORD
