Metadata-Version: 2.1
Name: chloryne
Version: 1.0.0
Summary: Another libsodium wrapper.
Home-page: https://gitee.com/origamizyt/chloryne
Author: origamizyt
License: MIT
Classifier: Development Status :: 3 - Alpha
Classifier: Intended Audience :: Developers
Classifier: License :: OSI Approved :: MIT License
Classifier: Topic :: Security :: Cryptography
Classifier: Programming Language :: Python :: 3
Requires-Python: >=3
License-File: LICENSE
